metis_walldisplay.py
metis_walldisplay-0.0.2.dist-info/DESCRIPTION.rst
metis_walldisplay-0.0.2.dist-info/METADATA
metis_walldisplay-0.0.2.dist-info/RECORD
metis_walldisplay-0.0.2.dist-info/WHEEL
metis_walldisplay-0.0.2.dist-info/metadata.json
metis_walldisplay-0.0.2.dist-info/top_level.txt
