Metadata-Version: 2.0
Name: metis-walldisplay
Version: 0.0.2
Summary: Communicate using serial to the wall display we have at metis
Home-page: https://github.com/nloomans/metis_walldisplay
Author: Noah Loomans
Author-email: UNKNOWN
License: UNKNOWN
Platform: UNKNOWN
